Metadata-Version: 2.1
Name: copilotsdk
Version: 0.1.1
Summary: A SDK for Webex troubleshooting copilot
Home-page: https://sqbu-github.cisco.com/WebexAI/webex-ai
Author: Won Zhou
Author-email: wanzhou@cisco.com
